supy_driver.libs/libgfortran-040039e1.so.5.0.0
supy_driver.libs/libquadmath-96973f99.so.0.0.0
supy_driver/version.py
supy_driver/suews_driver.cpython-37m-x86_64-linux-gnu.so
supy_driver/__init__.py
supy_driver-2022.2021a12.dist-info/top_level.txt
supy_driver-2022.2021a12.dist-info/WHEEL
supy_driver-2022.2021a12.dist-info/METADATA
supy_driver-2022.2021a12.dist-info/RECORD
