Metadata-Version: 2.1
Name: supy-driver
Version: 2022.2021a12
Summary: the SUEWS driver driven by f2py
Home-page: https://github.com/UMEP-dev/SuPy
Author: Ting Sun
Author-email: ting.sun@ucl.ac.uk
License: UNKNOWN
Platform: UNKNOWN
Requires-Python: >=3.7
Requires-Dist: numpy
